zirak/__init__.py
zirak-0.0.1.dist-info/LICENSE
zirak-0.0.1.dist-info/METADATA
zirak-0.0.1.dist-info/WHEEL
zirak-0.0.1.dist-info/top_level.txt
zirak-0.0.1.dist-info/RECORD
